geo_neural_network/smp_lib/__init__.py
geo_neural_network/smp_lib/smp_inference.py
geo_neural_network/smp_lib/smp_test.py
geo_neural_network/smp_lib/smp_train.py
geo_neural_network-1.0.5.dist-info/licenses/LICENSE
scripts/inference_geosmp.py
scripts/test_geosmp.py
scripts/train_geosmp.py
geo_neural_network-1.0.5.dist-info/METADATA
geo_neural_network-1.0.5.dist-info/WHEEL
geo_neural_network-1.0.5.dist-info/top_level.txt
geo_neural_network-1.0.5.dist-info/RECORD
